{
  "kind": "singleType",
  "collectionName": "homes",
  "info": {
    "singularName": "home",
    "pluralName": "homes",
    "displayName": "Home",
    "description": ""
  },
  "options": {
    "draftAndPublish": true
  },
  "pluginOptions": {
    "i18n": {
      "localized": true
    }
  },
  "attributes": {
    "slide_1": {
      "type": "media",
      "multiple": false,
      "required": false,
      "allowedTypes": [
        "images",
        "files",
        "videos",
        "audios"
      ],
      "pluginOptions": {
        "i18n": {
          "localized": true
        }
      }
    },
    "slide_2": {
      "type": "media",
      "multiple": false,
      "required": false,
      "allowedTypes": [
        "images",
        "files",
        "videos",
        "audios"
      ],
      "pluginOptions": {
        "i18n": {
          "localized": true
        }
      }
    },
    "slide_3": {
      "type": "media",
      "multiple": false,
      "required": false,
      "allowedTypes": [
        "images",
        "files",
        "videos",
        "audios"
      ],
      "pluginOptions": {
        "i18n": {
          "localized": true
        }
      }
    },
    "slide_4": {
      "type": "media",
      "multiple": false,
      "required": false,
      "allowedTypes": [
        "images",
        "files",
        "videos",
        "audios"
      ],
      "pluginOptions": {
        "i18n": {
          "localized": true
        }
      }
    },
    "slide_5": {
      "type": "media",
      "multiple": false,
      "required": false,
      "allowedTypes": [
        "images",
        "files",
        "videos",
        "audios"
      ],
      "pluginOptions": {
        "i18n": {
          "localized": true
        }
      }
    },
    "slide_6": {
      "type": "media",
      "multiple": false,
      "required": false,
      "allowedTypes": [
        "images",
        "files",
        "videos",
        "audios"
      ],
      "pluginOptions": {
        "i18n": {
          "localized": true
        }
      }
    },
    "slide_7": {
      "type": "media",
      "multiple": false,
      "required": false,
      "allowedTypes": [
        "images",
        "files",
        "videos",
        "audios"
      ],
      "pluginOptions": {
        "i18n": {
          "localized": true
        }
      }
    },
    "slide_8": {
      "type": "media",
      "multiple": false,
      "required": false,
      "allowedTypes": [
        "images",
        "files",
        "videos",
        "audios"
      ],
      "pluginOptions": {
        "i18n": {
          "localized": true
        }
      }
    },
    "slide_9": {
      "type": "media",
      "multiple": false,
      "required": false,
      "allowedTypes": [
        "images",
        "files",
        "videos",
        "audios"
      ],
      "pluginOptions": {
        "i18n": {
          "localized": true
        }
      }
    },
    "slide_10": {
      "type": "media",
      "multiple": false,
      "required": false,
      "allowedTypes": [
        "images",
        "files",
        "videos",
        "audios"
      ],
      "pluginOptions": {
        "i18n": {
          "localized": true
        }
      }
    },
    "slide_11": {
      "type": "media",
      "multiple": false,
      "required": false,
      "allowedTypes": [
        "images",
        "files",
        "videos",
        "audios"
      ],
      "pluginOptions": {
        "i18n": {
          "localized": true
        }
      }
    },
    "slide_12": {
      "type": "media",
      "multiple": false,
      "required": false,
      "allowedTypes": [
        "images",
        "files",
        "videos",
        "audios"
      ],
      "pluginOptions": {
        "i18n": {
          "localized": true
        }
      }
    },
    "slide_13": {
      "type": "media",
      "multiple": false,
      "required": false,
      "allowedTypes": [
        "images",
        "files",
        "videos",
        "audios"
      ],
      "pluginOptions": {
        "i18n": {
          "localized": true
        }
      }
    },
    "chefs_block": {
      "type": "component",
      "repeatable": false,
      "component": "chefs-block.chefs-block",
      "pluginOptions": {
        "i18n": {
          "localized": true
        }
      }
    }
  }
}
